random_topic/__init__.py
random_topic/random_topic.py
random_topic-0.1.2.dist-info/LICENSE
random_topic-0.1.2.dist-info/METADATA
random_topic-0.1.2.dist-info/WHEEL
random_topic-0.1.2.dist-info/top_level.txt
random_topic-0.1.2.dist-info/RECORD
