Metadata-Version: 2.1
Name: random-topic
Version: 0.1.2
Summary: module to fetch random topics for conversation
Home-page: https://github.com/johan-naizu/random_topic
Author: Johan Naizu
Author-email: johan@naizu.in
License: UNKNOWN
Project-URL: Bug Tracker, https://github.com/johan-naizu/random_topic/issues
Platform: UNKNOWN
Classifier: Programming Language :: Python :: 3
Classifier: License :: OSI Approved :: MIT License
Classifier: Operating System :: OS Independent
Requires-Python: >=3.6
